dataclass_coder/__init__.py
dataclass_coder/coder.py
dataclass_coder-0.0.3.dist-info/LICENSE
dataclass_coder-0.0.3.dist-info/METADATA
dataclass_coder-0.0.3.dist-info/WHEEL
dataclass_coder-0.0.3.dist-info/top_level.txt
dataclass_coder-0.0.3.dist-info/RECORD
