Metadata-Version: 2.1
Name: dataclass-coder
Version: 0.0.3
Summary: Lightweight and fast encoder/decoder for dataclass objects.
Home-page: https://github.com/h1ght1me/dataclass-coder
Author: h1ght1me
License: UNKNOWN
Platform: UNKNOWN
Classifier: Programming Language :: Python :: 3
Classifier: License :: OSI Approved :: MIT License
Classifier: Operating System :: OS Independent
Requires-Python: >=3.7
License-File: LICENSE
